{
    "DCHHEHNNEOO": [
      {
        "<IJIOLOGJGOA>k__BackingField": 0,
        "AJCFIEGDGKJ": false,
        "BABFEGLFEPM": "QuestDialogue/GCG/Venti_9534/Q6953406",
        "BHDGHCLPKJO": [],
        "BMDHAFAABKH": [],
        "CELNPBBKCGI": [],
        "COIDMPPBICE": 5,
        "CPAFCCNCCOK": false,
        "DDEHJILIFII": "TALK_NORMAL_QUEST",
        "DECAEDNMMPC": [],
        "DGIJIFMBOIA": false,
        "DMDMCIIFIEM": false,
        "DOIEFFDAABC": false,
        "EAFOGCGDOED": "LOGIC_NONE",
        "EHMJBIDGLBB": [],
        "ELEPNLBFNOP": [
          9534
        ],
        "ENDCCAOFDBD": false,
        "ENGEFMAPHMC": false,
        "EPIBANHLOCK": 0,
        "FAIEEGNFGFA": "TALK_MARK_NONE",
        "FHNJHCFCADD": 0,
        "FJIMHCGKKPJ": 6953406,
        "FKACMHGGNMB": "",
        "FMKFCHJMBAD": [],
        "FNGHGCCFKBI": 0,
        "GDBBHHGBICO": [
          {
            "_param": [
              "9534",
              "1"
            ],
            "_type": "QUEST_COND_GCG_NPC_TYPE"
          },
          {
            "_param": [
              "0"
            ],
            "_type": "QUEST_COND_GCG_INVITE_TYPE"
          }
        ],
        "GKFOKGDDOPJ": [],
        "GLPGLNAGPKE": "TALK_HERO_LOCAL",
        "HNMLDLAOLKH": [],
        "IBHGDPBJGLH": "PLAY_MODE_HOST",
        "ICCJNFGJNHH": 0,
        "INLNBHELFHP": false,
        "IPHECEFBJLA": false,
        "JBDFFJAEOJI": [],
        "JDKHHHNJCIC": [],
        "KAHECFNEOJL": "TALK_BEGIN_MANUAL",
        "KBNHFJHJAKO": [],
        "KMPGFFNMINA": 0,
        "LKPLDDJPACA": false,
        "LNJKPICKKAB": [
          6953408,
          6953409,
          6953418
        ],
        "MGOMOGBADOC": false,
        "NCEELENHOJO": 2940930106948275322,
        "NDFANEEKIDM": false,
        "OAKDNJLAPKM": false,
        "OBLJCEKJHHF": false,
        "OLCKDFIEGLI": 695340601,
        "PAJGOBABNGO": false,
        "PCHPODENOGB": 0
      },
      {
        "<IJIOLOGJGOA>k__BackingField": 0,
        "AJCFIEGDGKJ": false,
        "BABFEGLFEPM": "QuestDialogue/GCG/Venti_9534/Q6953407",
        "BHDGHCLPKJO": [],
        "BMDHAFAABKH": [],
        "CELNPBBKCGI": [],
        "COIDMPPBICE": 5,
        "CPAFCCNCCOK": false,
        "DDEHJILIFII": "TALK_NORMAL_QUEST",
        "DECAEDNMMPC": [],
        "DGIJIFMBOIA": false,
        "DMDMCIIFIEM": false,
        "DOIEFFDAABC": false,
        "EAFOGCGDOED": "LOGIC_NONE",
        "EHMJBIDGLBB": [],
        "ELEPNLBFNOP": [
          9534
        ],
        "ENDCCAOFDBD": false,
        "ENGEFMAPHMC": false,
        "EPIBANHLOCK": 0,
        "FAIEEGNFGFA": "TALK_MARK_NONE",
        "FHNJHCFCADD": 0,
        "FJIMHCGKKPJ": 6953407,
        "FKACMHGGNMB": "",
        "FMKFCHJMBAD": [],
        "FNGHGCCFKBI": 0,
        "GDBBHHGBICO": [],
        "GKFOKGDDOPJ": [],
        "GLPGLNAGPKE": "TALK_HERO_LOCAL",
        "HNMLDLAOLKH": [],
        "IBHGDPBJGLH": "PLAY_MODE_HOST",
        "ICCJNFGJNHH": 0,
        "INLNBHELFHP": false,
        "IPHECEFBJLA": false,
        "JBDFFJAEOJI": [],
        "JDKHHHNJCIC": [],
        "KAHECFNEOJL": "TALK_BEGIN_NONE",
        "KBNHFJHJAKO": [],
        "KMPGFFNMINA": 0,
        "LKPLDDJPACA": false,
        "LNJKPICKKAB": [
          6953408,
          6953409,
          6953418
        ],
        "MGOMOGBADOC": false,
        "NCEELENHOJO": 5183718115525001252,
        "NDFANEEKIDM": false,
        "OAKDNJLAPKM": false,
        "OBLJCEKJHHF": false,
        "OLCKDFIEGLI": 695340601,
        "PAJGOBABNGO": false,
        "PCHPODENOGB": 0
      },
      {
        "<IJIOLOGJGOA>k__BackingField": 0,
        "AJCFIEGDGKJ": false,
        "BABFEGLFEPM": "",
        "BHDGHCLPKJO": [],
        "BMDHAFAABKH": [],
        "CELNPBBKCGI": [],
        "COIDMPPBICE": 5,
        "CPAFCCNCCOK": false,
        "DDEHJILIFII": "TALK_NORMAL_QUEST",
        "DECAEDNMMPC": [],
        "DGIJIFMBOIA": false,
        "DMDMCIIFIEM": false,
        "DOIEFFDAABC": false,
        "EAFOGCGDOED": "LOGIC_NONE",
        "EHMJBIDGLBB": [],
        "ELEPNLBFNOP": [
          9534
        ],
        "ENDCCAOFDBD": false,
        "ENGEFMAPHMC": false,
        "EPIBANHLOCK": 0,
        "FAIEEGNFGFA": "TALK_MARK_NONE",
        "FHNJHCFCADD": 0,
        "FJIMHCGKKPJ": 6953408,
        "FKACMHGGNMB": "",
        "FMKFCHJMBAD": [],
        "FNGHGCCFKBI": 0,
        "GDBBHHGBICO": [],
        "GKFOKGDDOPJ": [],
        "GLPGLNAGPKE": "TALK_HERO_LOCAL",
        "HNMLDLAOLKH": [],
        "IBHGDPBJGLH": "PLAY_MODE_HOST",
        "ICCJNFGJNHH": 0,
        "INLNBHELFHP": false,
        "IPHECEFBJLA": false,
        "JBDFFJAEOJI": [],
        "JDKHHHNJCIC": [],
        "KAHECFNEOJL": "TALK_BEGIN_NONE",
        "KBNHFJHJAKO": [],
        "KMPGFFNMINA": 0,
        "LKPLDDJPACA": false,
        "LNJKPICKKAB": [],
        "MGOMOGBADOC": false,
        "NCEELENHOJO": 10275500868702344601,
        "NDFANEEKIDM": false,
        "OAKDNJLAPKM": false,
        "OBLJCEKJHHF": false,
        "OLCKDFIEGLI": 695340801,
        "PAJGOBABNGO": false,
        "PCHPODENOGB": 0
      },
      {
        "<IJIOLOGJGOA>k__BackingField": 0,
        "AJCFIEGDGKJ": false,
        "BABFEGLFEPM": "",
        "BHDGHCLPKJO": [],
        "BMDHAFAABKH": [],
        "CELNPBBKCGI": [],
        "COIDMPPBICE": 5,
        "CPAFCCNCCOK": false,
        "DDEHJILIFII": "TALK_NORMAL_QUEST",
        "DECAEDNMMPC": [],
        "DGIJIFMBOIA": false,
        "DMDMCIIFIEM": false,
        "DOIEFFDAABC": false,
        "EAFOGCGDOED": "LOGIC_NONE",
        "EHMJBIDGLBB": [],
        "ELEPNLBFNOP": [
          9534
        ],
        "ENDCCAOFDBD": false,
        "ENGEFMAPHMC": false,
        "EPIBANHLOCK": 0,
        "FAIEEGNFGFA": "TALK_MARK_NONE",
        "FHNJHCFCADD": 0,
        "FJIMHCGKKPJ": 6953409,
        "FKACMHGGNMB": "",
        "FMKFCHJMBAD": [],
        "FNGHGCCFKBI": 0,
        "GDBBHHGBICO": [],
        "GKFOKGDDOPJ": [],
        "GLPGLNAGPKE": "TALK_HERO_LOCAL",
        "HNMLDLAOLKH": [],
        "IBHGDPBJGLH": "PLAY_MODE_HOST",
        "ICCJNFGJNHH": 0,
        "INLNBHELFHP": false,
        "IPHECEFBJLA": false,
        "JBDFFJAEOJI": [],
        "JDKHHHNJCIC": [],
        "KAHECFNEOJL": "TALK_BEGIN_NONE",
        "KBNHFJHJAKO": [],
        "KMPGFFNMINA": 0,
        "LKPLDDJPACA": false,
        "LNJKPICKKAB": [
          6953407
        ],
        "MGOMOGBADOC": false,
        "NCEELENHOJO": 8989948993962722149,
        "NDFANEEKIDM": false,
        "OAKDNJLAPKM": false,
        "OBLJCEKJHHF": false,
        "OLCKDFIEGLI": 695340901,
        "PAJGOBABNGO": false,
        "PCHPODENOGB": 0
      },
      {
        "<IJIOLOGJGOA>k__BackingField": 0,
        "AJCFIEGDGKJ": false,
        "BABFEGLFEPM": "QuestDialogue/GCG/Venti_9534/Q6953410",
        "BHDGHCLPKJO": [],
        "BMDHAFAABKH": [],
        "CELNPBBKCGI": [],
        "COIDMPPBICE": 5,
        "CPAFCCNCCOK": false,
        "DDEHJILIFII": "TALK_NORMAL_QUEST",
        "DECAEDNMMPC": [],
        "DGIJIFMBOIA": false,
        "DMDMCIIFIEM": false,
        "DOIEFFDAABC": false,
        "EAFOGCGDOED": "LOGIC_NONE",
        "EHMJBIDGLBB": [],
        "ELEPNLBFNOP": [
          9534
        ],
        "ENDCCAOFDBD": false,
        "ENGEFMAPHMC": false,
        "EPIBANHLOCK": 0,
        "FAIEEGNFGFA": "TALK_MARK_NONE",
        "FHNJHCFCADD": 0,
        "FJIMHCGKKPJ": 6953410,
        "FKACMHGGNMB": "",
        "FMKFCHJMBAD": [],
        "FNGHGCCFKBI": 0,
        "GDBBHHGBICO": [],
        "GKFOKGDDOPJ": [],
        "GLPGLNAGPKE": "TALK_HERO_LOCAL",
        "HNMLDLAOLKH": [],
        "IBHGDPBJGLH": "PLAY_MODE_HOST",
        "ICCJNFGJNHH": 0,
        "INLNBHELFHP": false,
        "IPHECEFBJLA": false,
        "JBDFFJAEOJI": [],
        "JDKHHHNJCIC": [],
        "KAHECFNEOJL": "TALK_BEGIN_NONE",
        "KBNHFJHJAKO": [],
        "KMPGFFNMINA": 0,
        "LKPLDDJPACA": false,
        "LNJKPICKKAB": [],
        "MGOMOGBADOC": false,
        "NCEELENHOJO": 13898599117851604200,
        "NDFANEEKIDM": false,
        "OAKDNJLAPKM": false,
        "OBLJCEKJHHF": false,
        "OLCKDFIEGLI": 695341001,
        "PAJGOBABNGO": false,
        "PCHPODENOGB": 0
      },
      {
        "<IJIOLOGJGOA>k__BackingField": 0,
        "AJCFIEGDGKJ": false,
        "BABFEGLFEPM": "QuestDialogue/GCG/Venti_9534/Q6953411",
        "BHDGHCLPKJO": [],
        "BMDHAFAABKH": [],
        "CELNPBBKCGI": [],
        "COIDMPPBICE": 5,
        "CPAFCCNCCOK": false,
        "DDEHJILIFII": "TALK_NORMAL_QUEST",
        "DECAEDNMMPC": [],
        "DGIJIFMBOIA": false,
        "DMDMCIIFIEM": false,
        "DOIEFFDAABC": false,
        "EAFOGCGDOED": "LOGIC_NONE",
        "EHMJBIDGLBB": [],
        "ELEPNLBFNOP": [
          9534
        ],
        "ENDCCAOFDBD": false,
        "ENGEFMAPHMC": false,
        "EPIBANHLOCK": 0,
        "FAIEEGNFGFA": "TALK_MARK_NONE",
        "FHNJHCFCADD": 0,
        "FJIMHCGKKPJ": 6953411,
        "FKACMHGGNMB": "",
        "FMKFCHJMBAD": [],
        "FNGHGCCFKBI": 0,
        "GDBBHHGBICO": [],
        "GKFOKGDDOPJ": [],
        "GLPGLNAGPKE": "TALK_HERO_LOCAL",
        "HNMLDLAOLKH": [],
        "IBHGDPBJGLH": "PLAY_MODE_HOST",
        "ICCJNFGJNHH": 0,
        "INLNBHELFHP": false,
        "IPHECEFBJLA": false,
        "JBDFFJAEOJI": [],
        "JDKHHHNJCIC": [],
        "KAHECFNEOJL": "TALK_BEGIN_NONE",
        "KBNHFJHJAKO": [],
        "KMPGFFNMINA": 0,
        "LKPLDDJPACA": false,
        "LNJKPICKKAB": [],
        "MGOMOGBADOC": false,
        "NCEELENHOJO": 13591749441204451498,
        "NDFANEEKIDM": false,
        "OAKDNJLAPKM": false,
        "OBLJCEKJHHF": false,
        "OLCKDFIEGLI": 695341101,
        "PAJGOBABNGO": false,
        "PCHPODENOGB": 0
      },
      {
        "<IJIOLOGJGOA>k__BackingField": 0,
        "AJCFIEGDGKJ": false,
        "BABFEGLFEPM": "QuestDialogue/GCG/Venti_9534/Q6953412",
        "BHDGHCLPKJO": [],
        "BMDHAFAABKH": [],
        "CELNPBBKCGI": [],
        "COIDMPPBICE": 5,
        "CPAFCCNCCOK": false,
        "DDEHJILIFII": "TALK_NORMAL_QUEST",
        "DECAEDNMMPC": [],
        "DGIJIFMBOIA": false,
        "DMDMCIIFIEM": false,
        "DOIEFFDAABC": false,
        "EAFOGCGDOED": "LOGIC_NONE",
        "EHMJBIDGLBB": [],
        "ELEPNLBFNOP": [
          9534
        ],
        "ENDCCAOFDBD": false,
        "ENGEFMAPHMC": false,
        "EPIBANHLOCK": 0,
        "FAIEEGNFGFA": "TALK_MARK_NONE",
        "FHNJHCFCADD": 0,
        "FJIMHCGKKPJ": 6953412,
        "FKACMHGGNMB": "",
        "FMKFCHJMBAD": [],
        "FNGHGCCFKBI": 0,
        "GDBBHHGBICO": [
          {
            "_param": [
              "9534",
              "1"
            ],
            "_type": "QUEST_COND_GCG_NPC_TYPE"
          },
          {
            "_param": [
              "1"
            ],
            "_type": "QUEST_COND_GCG_INVITE_TYPE"
          }
        ],
        "GKFOKGDDOPJ": [],
        "GLPGLNAGPKE": "TALK_HERO_LOCAL",
        "HNMLDLAOLKH": [],
        "IBHGDPBJGLH": "PLAY_MODE_HOST",
        "ICCJNFGJNHH": 0,
        "INLNBHELFHP": false,
        "IPHECEFBJLA": false,
        "JBDFFJAEOJI": [],
        "JDKHHHNJCIC": [],
        "KAHECFNEOJL": "TALK_BEGIN_MANUAL",
        "KBNHFJHJAKO": [],
        "KMPGFFNMINA": 0,
        "LKPLDDJPACA": false,
        "LNJKPICKKAB": [
          6953414,
          6953415,
          6953418
        ],
        "MGOMOGBADOC": false,
        "NCEELENHOJO": 7708259755603218735,
        "NDFANEEKIDM": false,
        "OAKDNJLAPKM": false,
        "OBLJCEKJHHF": false,
        "OLCKDFIEGLI": 695341201,
        "PAJGOBABNGO": false,
        "PCHPODENOGB": 0
      },
      {
        "<IJIOLOGJGOA>k__BackingField": 0,
        "AJCFIEGDGKJ": false,
        "BABFEGLFEPM": "QuestDialogue/GCG/Venti_9534/Q6953413",
        "BHDGHCLPKJO": [],
        "BMDHAFAABKH": [],
        "CELNPBBKCGI": [],
        "COIDMPPBICE": 5,
        "CPAFCCNCCOK": false,
        "DDEHJILIFII": "TALK_NORMAL_QUEST",
        "DECAEDNMMPC": [],
        "DGIJIFMBOIA": false,
        "DMDMCIIFIEM": false,
        "DOIEFFDAABC": false,
        "EAFOGCGDOED": "LOGIC_NONE",
        "EHMJBIDGLBB": [],
        "ELEPNLBFNOP": [
          9534
        ],
        "ENDCCAOFDBD": false,
        "ENGEFMAPHMC": false,
        "EPIBANHLOCK": 0,
        "FAIEEGNFGFA": "TALK_MARK_NONE",
        "FHNJHCFCADD": 0,
        "FJIMHCGKKPJ": 6953413,
        "FKACMHGGNMB": "",
        "FMKFCHJMBAD": [],
        "FNGHGCCFKBI": 0,
        "GDBBHHGBICO": [],
        "GKFOKGDDOPJ": [],
        "GLPGLNAGPKE": "TALK_HERO_LOCAL",
        "HNMLDLAOLKH": [],
        "IBHGDPBJGLH": "PLAY_MODE_HOST",
        "ICCJNFGJNHH": 0,
        "INLNBHELFHP": false,
        "IPHECEFBJLA": false,
        "JBDFFJAEOJI": [],
        "JDKHHHNJCIC": [],
        "KAHECFNEOJL": "TALK_BEGIN_NONE",
        "KBNHFJHJAKO": [],
        "KMPGFFNMINA": 0,
        "LKPLDDJPACA": false,
        "LNJKPICKKAB": [
          6953414,
          6953415,
          6953418
        ],
        "MGOMOGBADOC": false,
        "NCEELENHOJO": 11354638645719444906,
        "NDFANEEKIDM": false,
        "OAKDNJLAPKM": false,
        "OBLJCEKJHHF": false,
        "OLCKDFIEGLI": 695341201,
        "PAJGOBABNGO": false,
        "PCHPODENOGB": 0
      },
      {
        "<IJIOLOGJGOA>k__BackingField": 0,
        "AJCFIEGDGKJ": false,
        "BABFEGLFEPM": "",
        "BHDGHCLPKJO": [],
        "BMDHAFAABKH": [],
        "CELNPBBKCGI": [],
        "COIDMPPBICE": 5,
        "CPAFCCNCCOK": false,
        "DDEHJILIFII": "TALK_NORMAL_QUEST",
        "DECAEDNMMPC": [],
        "DGIJIFMBOIA": false,
        "DMDMCIIFIEM": false,
        "DOIEFFDAABC": false,
        "EAFOGCGDOED": "LOGIC_NONE",
        "EHMJBIDGLBB": [],
        "ELEPNLBFNOP": [
          9534
        ],
        "ENDCCAOFDBD": false,
        "ENGEFMAPHMC": false,
        "EPIBANHLOCK": 0,
        "FAIEEGNFGFA": "TALK_MARK_NONE",
        "FHNJHCFCADD": 0,
        "FJIMHCGKKPJ": 6953414,
        "FKACMHGGNMB": "",
        "FMKFCHJMBAD": [],
        "FNGHGCCFKBI": 0,
        "GDBBHHGBICO": [],
        "GKFOKGDDOPJ": [],
        "GLPGLNAGPKE": "TALK_HERO_LOCAL",
        "HNMLDLAOLKH": [],
        "IBHGDPBJGLH": "PLAY_MODE_HOST",
        "ICCJNFGJNHH": 0,
        "INLNBHELFHP": false,
        "IPHECEFBJLA": false,
        "JBDFFJAEOJI": [],
        "JDKHHHNJCIC": [],
        "KAHECFNEOJL": "TALK_BEGIN_NONE",
        "KBNHFJHJAKO": [],
        "KMPGFFNMINA": 0,
        "LKPLDDJPACA": false,
        "LNJKPICKKAB": [],
        "MGOMOGBADOC": false,
        "NCEELENHOJO": 17345020613683364216,
        "NDFANEEKIDM": false,
        "OAKDNJLAPKM": false,
        "OBLJCEKJHHF": false,
        "OLCKDFIEGLI": 695341401,
        "PAJGOBABNGO": false,
        "PCHPODENOGB": 0
      },
      {
        "<IJIOLOGJGOA>k__BackingField": 0,
        "AJCFIEGDGKJ": false,
        "BABFEGLFEPM": "",
        "BHDGHCLPKJO": [],
        "BMDHAFAABKH": [],
        "CELNPBBKCGI": [],
        "COIDMPPBICE": 5,
        "CPAFCCNCCOK": false,
        "DDEHJILIFII": "TALK_NORMAL_QUEST",
        "DECAEDNMMPC": [],
        "DGIJIFMBOIA": false,
        "DMDMCIIFIEM": false,
        "DOIEFFDAABC": false,
        "EAFOGCGDOED": "LOGIC_NONE",
        "EHMJBIDGLBB": [],
        "ELEPNLBFNOP": [
          9534
        ],
        "ENDCCAOFDBD": false,
        "ENGEFMAPHMC": false,
        "EPIBANHLOCK": 0,
        "FAIEEGNFGFA": "TALK_MARK_NONE",
        "FHNJHCFCADD": 0,
        "FJIMHCGKKPJ": 6953415,
        "FKACMHGGNMB": "",
        "FMKFCHJMBAD": [],
        "FNGHGCCFKBI": 0,
        "GDBBHHGBICO": [],
        "GKFOKGDDOPJ": [],
        "GLPGLNAGPKE": "TALK_HERO_LOCAL",
        "HNMLDLAOLKH": [],
        "IBHGDPBJGLH": "PLAY_MODE_HOST",
        "ICCJNFGJNHH": 0,
        "INLNBHELFHP": false,
        "IPHECEFBJLA": false,
        "JBDFFJAEOJI": [],
        "JDKHHHNJCIC": [],
        "KAHECFNEOJL": "TALK_BEGIN_NONE",
        "KBNHFJHJAKO": [],
        "KMPGFFNMINA": 0,
        "LKPLDDJPACA": false,
        "LNJKPICKKAB": [
          6953413
        ],
        "MGOMOGBADOC": false,
        "NCEELENHOJO": 8180893975351299442,
        "NDFANEEKIDM": false,
        "OAKDNJLAPKM": false,
        "OBLJCEKJHHF": false,
        "OLCKDFIEGLI": 695341501,
        "PAJGOBABNGO": false,
        "PCHPODENOGB": 0
      },
      {
        "<IJIOLOGJGOA>k__BackingField": 0,
        "AJCFIEGDGKJ": false,
        "BABFEGLFEPM": "QuestDialogue/GCG/Venti_9534/Q6953416",
        "BHDGHCLPKJO": [],
        "BMDHAFAABKH": [],
        "CELNPBBKCGI": [],
        "COIDMPPBICE": 5,
        "CPAFCCNCCOK": false,
        "DDEHJILIFII": "TALK_NORMAL_QUEST",
        "DECAEDNMMPC": [],
        "DGIJIFMBOIA": false,
        "DMDMCIIFIEM": false,
        "DOIEFFDAABC": false,
        "EAFOGCGDOED": "LOGIC_NONE",
        "EHMJBIDGLBB": [],
        "ELEPNLBFNOP": [
          9534
        ],
        "ENDCCAOFDBD": false,
        "ENGEFMAPHMC": false,
        "EPIBANHLOCK": 0,
        "FAIEEGNFGFA": "TALK_MARK_NONE",
        "FHNJHCFCADD": 0,
        "FJIMHCGKKPJ": 6953416,
        "FKACMHGGNMB": "",
        "FMKFCHJMBAD": [],
        "FNGHGCCFKBI": 0,
        "GDBBHHGBICO": [],
        "GKFOKGDDOPJ": [],
        "GLPGLNAGPKE": "TALK_HERO_LOCAL",
        "HNMLDLAOLKH": [],
        "IBHGDPBJGLH": "PLAY_MODE_HOST",
        "ICCJNFGJNHH": 0,
        "INLNBHELFHP": false,
        "IPHECEFBJLA": false,
        "JBDFFJAEOJI": [],
        "JDKHHHNJCIC": [],
        "KAHECFNEOJL": "TALK_BEGIN_NONE",
        "KBNHFJHJAKO": [],
        "KMPGFFNMINA": 0,
        "LKPLDDJPACA": false,
        "LNJKPICKKAB": [],
        "MGOMOGBADOC": false,
        "NCEELENHOJO": 16994697532469408235,
        "NDFANEEKIDM": false,
        "OAKDNJLAPKM": false,
        "OBLJCEKJHHF": false,
        "OLCKDFIEGLI": 695341601,
        "PAJGOBABNGO": false,
        "PCHPODENOGB": 0
      },
      {
        "<IJIOLOGJGOA>k__BackingField": 0,
        "AJCFIEGDGKJ": false,
        "BABFEGLFEPM": "QuestDialogue/GCG/Venti_9534/Q6953417",
        "BHDGHCLPKJO": [],
        "BMDHAFAABKH": [],
        "CELNPBBKCGI": [],
        "COIDMPPBICE": 5,
        "CPAFCCNCCOK": false,
        "DDEHJILIFII": "TALK_NORMAL_QUEST",
        "DECAEDNMMPC": [],
        "DGIJIFMBOIA": false,
        "DMDMCIIFIEM": false,
        "DOIEFFDAABC": false,
        "EAFOGCGDOED": "LOGIC_NONE",
        "EHMJBIDGLBB": [],
        "ELEPNLBFNOP": [
          9534
        ],
        "ENDCCAOFDBD": false,
        "ENGEFMAPHMC": false,
        "EPIBANHLOCK": 0,
        "FAIEEGNFGFA": "TALK_MARK_NONE",
        "FHNJHCFCADD": 0,
        "FJIMHCGKKPJ": 6953417,
        "FKACMHGGNMB": "",
        "FMKFCHJMBAD": [],
        "FNGHGCCFKBI": 0,
        "GDBBHHGBICO": [],
        "GKFOKGDDOPJ": [],
        "GLPGLNAGPKE": "TALK_HERO_LOCAL",
        "HNMLDLAOLKH": [],
        "IBHGDPBJGLH": "PLAY_MODE_HOST",
        "ICCJNFGJNHH": 0,
        "INLNBHELFHP": false,
        "IPHECEFBJLA": false,
        "JBDFFJAEOJI": [],
        "JDKHHHNJCIC": [],
        "KAHECFNEOJL": "TALK_BEGIN_NONE",
        "KBNHFJHJAKO": [],
        "KMPGFFNMINA": 0,
        "LKPLDDJPACA": false,
        "LNJKPICKKAB": [],
        "MGOMOGBADOC": false,
        "NCEELENHOJO": 8237339408743858103,
        "NDFANEEKIDM": false,
        "OAKDNJLAPKM": false,
        "OBLJCEKJHHF": false,
        "OLCKDFIEGLI": 695341701,
        "PAJGOBABNGO": false,
        "PCHPODENOGB": 0
      },
      {
        "<IJIOLOGJGOA>k__BackingField": 0,
        "AJCFIEGDGKJ": false,
        "BABFEGLFEPM": "",
        "BHDGHCLPKJO": [],
        "BMDHAFAABKH": [],
        "CELNPBBKCGI": [],
        "COIDMPPBICE": 5,
        "CPAFCCNCCOK": false,
        "DDEHJILIFII": "TALK_NORMAL_QUEST",
        "DECAEDNMMPC": [],
        "DGIJIFMBOIA": false,
        "DMDMCIIFIEM": false,
        "DOIEFFDAABC": false,
        "EAFOGCGDOED": "LOGIC_NONE",
        "EHMJBIDGLBB": [],
        "ELEPNLBFNOP": [
          9534
        ],
        "ENDCCAOFDBD": false,
        "ENGEFMAPHMC": false,
        "EPIBANHLOCK": 0,
        "FAIEEGNFGFA": "TALK_MARK_NONE",
        "FHNJHCFCADD": 0,
        "FJIMHCGKKPJ": 6953418,
        "FKACMHGGNMB": "",
        "FMKFCHJMBAD": [],
        "FNGHGCCFKBI": 0,
        "GDBBHHGBICO": [],
        "GKFOKGDDOPJ": [],
        "GLPGLNAGPKE": "TALK_HERO_LOCAL",
        "HNMLDLAOLKH": [],
        "IBHGDPBJGLH": "PLAY_MODE_HOST",
        "ICCJNFGJNHH": 0,
        "INLNBHELFHP": false,
        "IPHECEFBJLA": false,
        "JBDFFJAEOJI": [],
        "JDKHHHNJCIC": [],
        "KAHECFNEOJL": "TALK_BEGIN_NONE",
        "KBNHFJHJAKO": [],
        "KMPGFFNMINA": 0,
        "LKPLDDJPACA": false,
        "LNJKPICKKAB": [],
        "MGOMOGBADOC": false,
        "NCEELENHOJO": 18269091947145984040,
        "NDFANEEKIDM": false,
        "OAKDNJLAPKM": false,
        "OBLJCEKJHHF": false,
        "OLCKDFIEGLI": 695341801,
        "PAJGOBABNGO": false,
        "PCHPODENOGB": 0
      }
    ],
    "ELEPNLBFNOP": 9534
  }