{
  "IKECHKLEFFK": [
    {
      "FPHEKMJNBDI": {
        "LAPLJEJIGID": "",
        "ODAEKEKONOP": "",
        "MEGMIMEDODJ": "QUEST_GUIDE_HINT_NONE"
      },
      "PGELADPAKLA": [
        {
          "PGEONGPJEPN": "",
          "KFDJJBPNIHG": [
            2401901,
            0
          ],
          "EIOBNIHPLNG": 0,
          "MEGMIMEDODJ": "QUEST_CONTENT_COMPLETE_TALK"
        }
      ],
      "JPNGNAKJBHI": [
        340201
      ],
      "JHJNAFCPBHM": [],
      "AAOOAIKEFFP": "",
      "HJDJMNGCKBJ": [],
      "FLMNHDEBPEN": "",
      "OEIHEDKBHGE": [],
      "EMHJFNKHAEN": [],
      "HMLHCHOMKJG": [
        5084
      ],
      "OJCGKOFEKAJ": {
        "ECNEHNJJDJM": "",
        "HEBCJCMDEDP": "",
        "KFDJJBPNIHG": [
          "5084"
        ],
        "JFCEABKGEJO": "QUEST_GUIDE_AUTO_NONE",
        "HAKDPJDMMEJ": 0,
        "FNFIEMBKLEE": 3,
        "MAHPGKFCAME": 0,
        "GOMAFDHKMNN": 0,
        "MEGMIMEDODJ": "QUEST_GUIDE_NPC",
        "BGGNIDPMKFP": "QUEST_GUIDE_IN_SCENE_STYLE_NONE",
        "FHPLLIKLAAL": "QUEST_GUIDE_AREA_STYLE_DEFAULT",
        "CMHADOJIPNO": "QUEST_GUIDE_INDICATOR_STYLE_NONE",
        "LNENHAIIJPO": "NONE",
        "ADGNKEBCCGJ": "QUEST_GUIDE_STYLE_TARGET",
        "LOEGKGEFBBD": "QUEST_GUIDE_LAYER_SCENE"
      },
      "IJBIPKFMFAE": 0,
      "PJHBHFEKIBP": false,
      "PBDDIJBBGCN": false,
      "FPILKGGJOND": false,
      "HLOLLJJCDKK": true,
      "FAPKBAGMFND": "QUEST_SHOW",
      "JLBOIHKAILH": "DEFAULT",
      "BPJIGOFJLBK": 0,
      "CBOGAFHNHNI": 24019,
      "JCBGLEECOJF": false,
      "JOBNFBNOPOJ": false,
      "IBOKECEBLGE": "NONE",
      "PKJEGLKMEID": "BAN_GROUP_INVALID",
      "PAJNNJAGIDK": 0,
      "FCJEELDOLGE": "QUEST_SHOW",
      "OKAFIEPPFJD": "QUEST_SHOW",
      "EDPMKKJIKCJ": 1,
      "LAFBPKMMBHD": 2401901,
      "IODALFMJPCK": "QUEST_GUIDE_ITEM_ENABLE",
      "NPIDOLEHAGF": 0,
      "JDFENJAFCPF": 1715010084,
      "LGANAHEDEJD": 0,
      "KHPCFMHKOKE": 0
    },
    {
      "FPHEKMJNBDI": {
        "LAPLJEJIGID": "",
        "ODAEKEKONOP": "",
        "MEGMIMEDODJ": "QUEST_GUIDE_HINT_NONE"
      },
      "PGELADPAKLA": [
        {
          "PGEONGPJEPN": "240190201",
          "KFDJJBPNIHG": [
            0,
            0
          ],
          "EIOBNIHPLNG": 1,
          "MEGMIMEDODJ": "QUEST_CONTENT_LUA_NOTIFY"
        }
      ],
      "JPNGNAKJBHI": [
        340201
      ],
      "JHJNAFCPBHM": [],
      "AAOOAIKEFFP": "",
      "HJDJMNGCKBJ": [
        {
          "PGEONGPJEPN": "2401906Fail",
          "KFDJJBPNIHG": [
            0,
            0
          ],
          "EIOBNIHPLNG": 1,
          "MEGMIMEDODJ": "QUEST_CONTENT_LUA_NOTIFY"
        }
      ],
      "FLMNHDEBPEN": "",
      "OEIHEDKBHGE": [
        {
          "KFDJJBPNIHG": [
            "120487",
            "1"
          ],
          "MEGMIMEDODJ": "QUEST_EXEC_DEL_PACK_ITEM"
        }
      ],
      "EMHJFNKHAEN": [],
      "HMLHCHOMKJG": [
        5084
      ],
      "OJCGKOFEKAJ": {
        "ECNEHNJJDJM": "",
        "HEBCJCMDEDP": "",
        "KFDJJBPNIHG": [
          "[3_5568:3737.775,479.657,3700.179,0.002,334.876,359.908]"
        ],
        "JFCEABKGEJO": "QUEST_GUIDE_AUTO_NONE",
        "HAKDPJDMMEJ": 0,
        "FNFIEMBKLEE": 3,
        "MAHPGKFCAME": 0,
        "GOMAFDHKMNN": 0,
        "MEGMIMEDODJ": "QUEST_GUIDE_LOCATION",
        "BGGNIDPMKFP": "QUEST_GUIDE_IN_SCENE_STYLE_NONE",
        "FHPLLIKLAAL": "QUEST_GUIDE_AREA_STYLE_DEFAULT",
        "CMHADOJIPNO": "QUEST_GUIDE_INDICATOR_STYLE_NONE",
        "LNENHAIIJPO": "NONE",
        "ADGNKEBCCGJ": "QUEST_GUIDE_STYLE_POINT",
        "LOEGKGEFBBD": "QUEST_GUIDE_LAYER_SCENE"
      },
      "IJBIPKFMFAE": 0,
      "PJHBHFEKIBP": false,
      "PBDDIJBBGCN": false,
      "FPILKGGJOND": false,
      "HLOLLJJCDKK": true,
      "FAPKBAGMFND": "QUEST_SHOW",
      "JLBOIHKAILH": "DEFAULT",
      "BPJIGOFJLBK": 0,
      "CBOGAFHNHNI": 24019,
      "JCBGLEECOJF": false,
      "JOBNFBNOPOJ": false,
      "IBOKECEBLGE": "NONE",
      "PKJEGLKMEID": "BAN_GROUP_INVALID",
      "PAJNNJAGIDK": 0,
      "FCJEELDOLGE": "QUEST_SHOW",
      "OKAFIEPPFJD": "QUEST_SHOW",
      "EDPMKKJIKCJ": 2,
      "LAFBPKMMBHD": 2401902,
      "IODALFMJPCK": "QUEST_GUIDE_ITEM_ENABLE",
      "NPIDOLEHAGF": 0,
      "JDFENJAFCPF": 3903249060,
      "LGANAHEDEJD": 0,
      "KHPCFMHKOKE": 0
    },
    {
      "FPHEKMJNBDI": {
        "LAPLJEJIGID": "",
        "ODAEKEKONOP": "",
        "MEGMIMEDODJ": "QUEST_GUIDE_HINT_NONE"
      },
      "PGELADPAKLA": [
        {
          "PGEONGPJEPN": "",
          "KFDJJBPNIHG": [
            2401903,
            0
          ],
          "EIOBNIHPLNG": 0,
          "MEGMIMEDODJ": "QUEST_CONTENT_COMPLETE_TALK"
        },
        {
          "PGEONGPJEPN": "",
          "KFDJJBPNIHG": [
            2401908,
            0
          ],
          "EIOBNIHPLNG": 0,
          "MEGMIMEDODJ": "QUEST_CONTENT_COMPLETE_TALK"
        }
      ],
      "JPNGNAKJBHI": [
        340201
      ],
      "JHJNAFCPBHM": [],
      "AAOOAIKEFFP": "",
      "HJDJMNGCKBJ": [],
      "FLMNHDEBPEN": "",
      "OEIHEDKBHGE": [
        {
          "KFDJJBPNIHG": [
            "120487"
          ],
          "MEGMIMEDODJ": "QUEST_EXEC_DEL_ALL_SPECIFIC_PACK_ITEM"
        },
        {
          "KFDJJBPNIHG": [
            "133402057",
            "0"
          ],
          "MEGMIMEDODJ": "QUEST_EXEC_UNREGISTER_DYNAMIC_GROUP"
        },
        {
          "KFDJJBPNIHG": [
            "43171"
          ],
          "MEGMIMEDODJ": "QUEST_EXEC_NOTIFY_DAILY_TASK"
        }
      ],
      "EMHJFNKHAEN": [],
      "HMLHCHOMKJG": [
        5084
      ],
      "OJCGKOFEKAJ": {
        "ECNEHNJJDJM": "",
        "HEBCJCMDEDP": "",
        "KFDJJBPNIHG": [
          "5084"
        ],
        "JFCEABKGEJO": "QUEST_GUIDE_AUTO_NONE",
        "HAKDPJDMMEJ": 0,
        "FNFIEMBKLEE": 3,
        "MAHPGKFCAME": 0,
        "GOMAFDHKMNN": 0,
        "MEGMIMEDODJ": "QUEST_GUIDE_NPC",
        "BGGNIDPMKFP": "QUEST_GUIDE_IN_SCENE_STYLE_NONE",
        "FHPLLIKLAAL": "QUEST_GUIDE_AREA_STYLE_DEFAULT",
        "CMHADOJIPNO": "QUEST_GUIDE_INDICATOR_STYLE_NONE",
        "LNENHAIIJPO": "NONE",
        "ADGNKEBCCGJ": "QUEST_GUIDE_STYLE_TARGET",
        "LOEGKGEFBBD": "QUEST_GUIDE_LAYER_SCENE"
      },
      "IJBIPKFMFAE": 0,
      "PJHBHFEKIBP": false,
      "PBDDIJBBGCN": true,
      "FPILKGGJOND": false,
      "HLOLLJJCDKK": true,
      "FAPKBAGMFND": "QUEST_SHOW",
      "JLBOIHKAILH": "DEFAULT",
      "BPJIGOFJLBK": 0,
      "CBOGAFHNHNI": 24019,
      "JCBGLEECOJF": false,
      "JOBNFBNOPOJ": false,
      "IBOKECEBLGE": "NONE",
      "PKJEGLKMEID": "BAN_GROUP_INVALID",
      "PAJNNJAGIDK": 0,
      "FCJEELDOLGE": "QUEST_SHOW",
      "OKAFIEPPFJD": "QUEST_SHOW",
      "EDPMKKJIKCJ": 3,
      "LAFBPKMMBHD": 2401903,
      "IODALFMJPCK": "QUEST_GUIDE_ITEM_ENABLE",
      "NPIDOLEHAGF": 0,
      "JDFENJAFCPF": 2688284260,
      "LGANAHEDEJD": 0,
      "KHPCFMHKOKE": 0
    }
  ],
  "EOHJIHHMBAN": [],
  "EGDDLPOMLBH": [],
  "JBCAOAFIHCD": [],
  "GIBODJFDPAF": [],
  "MEGMIMEDODJ": "IQ",
  "JILHIMLENJK": 0,
  "MBGJPPMHPOH": 0,
  "LNOBNKJACCL": false,
  "NPMLGCFEMEP": true,
  "GMOMCKNPBGE": 24019,
  "OMLHINNGFAE": "MAINQUEST_TAG_NONE",
  "DMKHKJJFOAA": 0,
  "ALLMCLJBBDM": 3818857199,
  "JDFENJAFCPF": 1887772358,
  "JFINEFAPKMC": 43171,
  "CNEAOJLFBOO": 0,
  "FAPKBAGMFND": "QUEST_SHOW"
}