{
  "0425f51d-292a-48bb-89b2-718739d150ff": {
    "FBACJKDNMJE": [],
    "KLHFLAODHIE": [],
    "DPNKFDDEGNE": "7d8f7673-5d3b-44ea-bfd3-60443acdd436",
    "NEJBKIJIBHJ": [
      {
        "NKPOOPONEHG": "VO_AQ\\VO_lauma\\vo_NKAQ003_20_lauma_04.wem",
        "FBCCEBGJEDB": "",
        "DAGKBDACGKN": "",
        "OFIPNHHFMIN": 1,
        "ILELCCFFKMG": 0
      }
    ],
    "LNBFOPNLLDB": "0425f51d-292a-48bb-89b2-718739d150ff",
    "JOMDCMBGNMB": "Dialog",
    "LDKLLMBOPIL": 0,
    "IHJNILOFHDI": 0,
    "DINIOGNDACL": 1,
    "BKGHEBIGJNC": 60022224,
    "CLILOKOGFCH": 0,
    "OAOMGAPFFMC": 2,
    "FGDBNGAMIBE": 0,
    "NLNHEEOBGLH": 0,
    "ONCKINKBDMD": 0,
    "IEDLBAGHKGK": 0,
    "FBNNIOINNNO": false,
    "HCCLMPGEBLE": false,
    "DJHJHPLAJNG": false,
    "GIAFBIIBGOE": false
  },
  "05850bd0-ac6f-4f0a-ae03-aa699ad86110": {
    "FBACJKDNMJE": [],
    "KLHFLAODHIE": [],
    "DPNKFDDEGNE": "7d8f7673-5d3b-44ea-bfd3-60443acdd436",
    "NEJBKIJIBHJ": [
      {
        "NKPOOPONEHG": "VO_AQ\\VO_lauma\\vo_NKAQ003_20_lauma_01.wem",
        "FBCCEBGJEDB": "",
        "DAGKBDACGKN": "",
        "OFIPNHHFMIN": 1,
        "ILELCCFFKMG": 0
      }
    ],
    "LNBFOPNLLDB": "05850bd0-ac6f-4f0a-ae03-aa699ad86110",
    "JOMDCMBGNMB": "Dialog",
    "LDKLLMBOPIL": 0,
    "IHJNILOFHDI": 0,
    "DINIOGNDACL": 1,
    "BKGHEBIGJNC": 60022210,
    "CLILOKOGFCH": 0,
    "OAOMGAPFFMC": 2,
    "FGDBNGAMIBE": 0,
    "NLNHEEOBGLH": 0,
    "ONCKINKBDMD": 0,
    "IEDLBAGHKGK": 0,
    "FBNNIOINNNO": false,
    "HCCLMPGEBLE": false,
    "DJHJHPLAJNG": false,
    "GIAFBIIBGOE": false
  },
  "22ae17d4-325f-4499-a2bf-efa0381a58f0": {
    "FBACJKDNMJE": [],
    "KLHFLAODHIE": [],
    "DPNKFDDEGNE": "7d8f7673-5d3b-44ea-bfd3-60443acdd436",
    "NEJBKIJIBHJ": [
      {
        "NKPOOPONEHG": "VO_AQ\\VO_marionette\\vo_NKAQ003_20_marionette_08.wem",
        "FBCCEBGJEDB": "",
        "DAGKBDACGKN": "",
        "OFIPNHHFMIN": 1,
        "ILELCCFFKMG": 0
      }
    ],
    "LNBFOPNLLDB": "22ae17d4-325f-4499-a2bf-efa0381a58f0",
    "JOMDCMBGNMB": "Dialog",
    "LDKLLMBOPIL": 0,
    "IHJNILOFHDI": 0,
    "DINIOGNDACL": 1,
    "BKGHEBIGJNC": 60022215,
    "CLILOKOGFCH": 0,
    "OAOMGAPFFMC": 2,
    "FGDBNGAMIBE": 0,
    "NLNHEEOBGLH": 0,
    "ONCKINKBDMD": 0,
    "IEDLBAGHKGK": 0,
    "FBNNIOINNNO": false,
    "HCCLMPGEBLE": false,
    "DJHJHPLAJNG": false,
    "GIAFBIIBGOE": false
  },
  "2afb30b5-e2ff-47b5-a864-ee77de4a9957": {
    "FBACJKDNMJE": [],
    "KLHFLAODHIE": [],
    "DPNKFDDEGNE": "7d8f7673-5d3b-44ea-bfd3-60443acdd436",
    "NEJBKIJIBHJ": [
      {
        "NKPOOPONEHG": "VO_AQ\\VO_marionette\\vo_NKAQ003_20_marionette_03.wem",
        "FBCCEBGJEDB": "",
        "DAGKBDACGKN": "",
        "OFIPNHHFMIN": 1,
        "ILELCCFFKMG": 0
      }
    ],
    "LNBFOPNLLDB": "2afb30b5-e2ff-47b5-a864-ee77de4a9957",
    "JOMDCMBGNMB": "Dialog",
    "LDKLLMBOPIL": 0,
    "IHJNILOFHDI": 0,
    "DINIOGNDACL": 1,
    "BKGHEBIGJNC": 60022203,
    "CLILOKOGFCH": 0,
    "OAOMGAPFFMC": 2,
    "FGDBNGAMIBE": 0,
    "NLNHEEOBGLH": 0,
    "ONCKINKBDMD": 0,
    "IEDLBAGHKGK": 0,
    "FBNNIOINNNO": false,
    "HCCLMPGEBLE": false,
    "DJHJHPLAJNG": false,
    "GIAFBIIBGOE": false
  },
  "31fb46d1-56e0-4c78-beaf-a514757d3de4": {
    "FBACJKDNMJE": [],
    "KLHFLAODHIE": [],
    "DPNKFDDEGNE": "7d8f7673-5d3b-44ea-bfd3-60443acdd436",
    "NEJBKIJIBHJ": [
      {
        "NKPOOPONEHG": "VO_AQ\\VO_marionette\\vo_NKAQ003_20_marionette_11.wem",
        "FBCCEBGJEDB": "",
        "DAGKBDACGKN": "",
        "OFIPNHHFMIN": 1,
        "ILELCCFFKMG": 0
      }
    ],
    "LNBFOPNLLDB": "31fb46d1-56e0-4c78-beaf-a514757d3de4",
    "JOMDCMBGNMB": "Dialog",
    "LDKLLMBOPIL": 0,
    "IHJNILOFHDI": 0,
    "DINIOGNDACL": 1,
    "BKGHEBIGJNC": 60022218,
    "CLILOKOGFCH": 0,
    "OAOMGAPFFMC": 2,
    "FGDBNGAMIBE": 0,
    "NLNHEEOBGLH": 0,
    "ONCKINKBDMD": 0,
    "IEDLBAGHKGK": 0,
    "FBNNIOINNNO": false,
    "HCCLMPGEBLE": false,
    "DJHJHPLAJNG": false,
    "GIAFBIIBGOE": false
  },
  "35e6077e-ba49-4e74-a938-afac8f16ca19": {
    "FBACJKDNMJE": [],
    "KLHFLAODHIE": [],
    "DPNKFDDEGNE": "7d8f7673-5d3b-44ea-bfd3-60443acdd436",
    "NEJBKIJIBHJ": [
      {
        "NKPOOPONEHG": "VO_AQ\\VO_marionette\\vo_NKAQ003_20_marionette_06.wem",
        "FBCCEBGJEDB": "",
        "DAGKBDACGKN": "",
        "OFIPNHHFMIN": 1,
        "ILELCCFFKMG": 0
      }
    ],
    "LNBFOPNLLDB": "35e6077e-ba49-4e74-a938-afac8f16ca19",
    "JOMDCMBGNMB": "Dialog",
    "LDKLLMBOPIL": 0,
    "IHJNILOFHDI": 0,
    "DINIOGNDACL": 1,
    "BKGHEBIGJNC": 60022212,
    "CLILOKOGFCH": 0,
    "OAOMGAPFFMC": 2,
    "FGDBNGAMIBE": 0,
    "NLNHEEOBGLH": 0,
    "ONCKINKBDMD": 0,
    "IEDLBAGHKGK": 0,
    "FBNNIOINNNO": false,
    "HCCLMPGEBLE": false,
    "DJHJHPLAJNG": false,
    "GIAFBIIBGOE": false
  },
  "3eea27c5-ff36-41b3-a820-7896dbe7f9cc": {
    "FBACJKDNMJE": [],
    "KLHFLAODHIE": [],
    "DPNKFDDEGNE": "7d8f7673-5d3b-44ea-bfd3-60443acdd436",
    "NEJBKIJIBHJ": [
      {
        "NKPOOPONEHG": "VO_AQ\\VO_marionette\\vo_NKAQ003_20_marionette_07.wem",
        "FBCCEBGJEDB": "",
        "DAGKBDACGKN": "",
        "OFIPNHHFMIN": 1,
        "ILELCCFFKMG": 0
      }
    ],
    "LNBFOPNLLDB": "3eea27c5-ff36-41b3-a820-7896dbe7f9cc",
    "JOMDCMBGNMB": "Dialog",
    "LDKLLMBOPIL": 0,
    "IHJNILOFHDI": 0,
    "DINIOGNDACL": 1,
    "BKGHEBIGJNC": 60022213,
    "CLILOKOGFCH": 0,
    "OAOMGAPFFMC": 2,
    "FGDBNGAMIBE": 0,
    "NLNHEEOBGLH": 0,
    "ONCKINKBDMD": 0,
    "IEDLBAGHKGK": 0,
    "FBNNIOINNNO": false,
    "HCCLMPGEBLE": false,
    "DJHJHPLAJNG": false,
    "GIAFBIIBGOE": false
  },
  "5926d955-a4d7-4945-b2ed-02ee9f946dca": {
    "FBACJKDNMJE": [],
    "KLHFLAODHIE": [],
    "DPNKFDDEGNE": "7d8f7673-5d3b-44ea-bfd3-60443acdd436",
    "NEJBKIJIBHJ": [
      {
        "NKPOOPONEHG": "VO_AQ\\VO_jahoda\\vo_NKAQ003_20_jahoda_02.wem",
        "FBCCEBGJEDB": "",
        "DAGKBDACGKN": "",
        "OFIPNHHFMIN": 1,
        "ILELCCFFKMG": 0
      }
    ],
    "LNBFOPNLLDB": "5926d955-a4d7-4945-b2ed-02ee9f946dca",
    "JOMDCMBGNMB": "Dialog",
    "LDKLLMBOPIL": 0,
    "IHJNILOFHDI": 0,
    "DINIOGNDACL": 1,
    "BKGHEBIGJNC": 60022207,
    "CLILOKOGFCH": 0,
    "OAOMGAPFFMC": 2,
    "FGDBNGAMIBE": 0,
    "NLNHEEOBGLH": 0,
    "ONCKINKBDMD": 0,
    "IEDLBAGHKGK": 0,
    "FBNNIOINNNO": false,
    "HCCLMPGEBLE": false,
    "DJHJHPLAJNG": false,
    "GIAFBIIBGOE": false
  },
  "6601be0a-6c8c-41c5-a065-ae99bbca7c81": {
    "FBACJKDNMJE": [],
    "KLHFLAODHIE": [],
    "DPNKFDDEGNE": "7d8f7673-5d3b-44ea-bfd3-60443acdd436",
    "NEJBKIJIBHJ": [
      {
        "NKPOOPONEHG": "VO_AQ\\VO_marionette\\vo_NKAQ003_20_marionette_04.wem",
        "FBCCEBGJEDB": "",
        "DAGKBDACGKN": "",
        "OFIPNHHFMIN": 1,
        "ILELCCFFKMG": 0
      }
    ],
    "LNBFOPNLLDB": "6601be0a-6c8c-41c5-a065-ae99bbca7c81",
    "JOMDCMBGNMB": "Dialog",
    "LDKLLMBOPIL": 0,
    "IHJNILOFHDI": 0,
    "DINIOGNDACL": 1,
    "BKGHEBIGJNC": 60022205,
    "CLILOKOGFCH": 0,
    "OAOMGAPFFMC": 2,
    "FGDBNGAMIBE": 0,
    "NLNHEEOBGLH": 0,
    "ONCKINKBDMD": 0,
    "IEDLBAGHKGK": 0,
    "FBNNIOINNNO": false,
    "HCCLMPGEBLE": false,
    "DJHJHPLAJNG": false,
    "GIAFBIIBGOE": false
  },
  "727b85c1-2ba2-4887-8454-7b9310ad9911": {
    "FBACJKDNMJE": [],
    "KLHFLAODHIE": [],
    "DPNKFDDEGNE": "7d8f7673-5d3b-44ea-bfd3-60443acdd436",
    "NEJBKIJIBHJ": [
      {
        "NKPOOPONEHG": "VO_AQ\\VO_marionette\\vo_NKAQ003_20_marionette_02.wem",
        "FBCCEBGJEDB": "",
        "DAGKBDACGKN": "",
        "OFIPNHHFMIN": 1,
        "ILELCCFFKMG": 0
      }
    ],
    "LNBFOPNLLDB": "727b85c1-2ba2-4887-8454-7b9310ad9911",
    "JOMDCMBGNMB": "Dialog",
    "LDKLLMBOPIL": 0,
    "IHJNILOFHDI": 0,
    "DINIOGNDACL": 1,
    "BKGHEBIGJNC": 60022202,
    "CLILOKOGFCH": 0,
    "OAOMGAPFFMC": 2,
    "FGDBNGAMIBE": 0,
    "NLNHEEOBGLH": 0,
    "ONCKINKBDMD": 0,
    "IEDLBAGHKGK": 0,
    "FBNNIOINNNO": false,
    "HCCLMPGEBLE": false,
    "DJHJHPLAJNG": false,
    "GIAFBIIBGOE": false
  },
  "732f1bad-58af-41a4-bcf2-8fc000c479f4": {
    "FBACJKDNMJE": [],
    "KLHFLAODHIE": [],
    "DPNKFDDEGNE": "7d8f7673-5d3b-44ea-bfd3-60443acdd436",
    "NEJBKIJIBHJ": [
      {
        "NKPOOPONEHG": "VO_AQ\\VO_paimon\\vo_NKAQ003_20_paimon_02.wem",
        "FBCCEBGJEDB": "",
        "DAGKBDACGKN": "",
        "OFIPNHHFMIN": 1,
        "ILELCCFFKMG": 0
      }
    ],
    "LNBFOPNLLDB": "732f1bad-58af-41a4-bcf2-8fc000c479f4",
    "JOMDCMBGNMB": "Dialog",
    "LDKLLMBOPIL": 0,
    "IHJNILOFHDI": 0,
    "DINIOGNDACL": 1,
    "BKGHEBIGJNC": 60022222,
    "CLILOKOGFCH": 0,
    "OAOMGAPFFMC": 2,
    "FGDBNGAMIBE": 0,
    "NLNHEEOBGLH": 0,
    "ONCKINKBDMD": 0,
    "IEDLBAGHKGK": 0,
    "FBNNIOINNNO": false,
    "HCCLMPGEBLE": false,
    "DJHJHPLAJNG": false,
    "GIAFBIIBGOE": false
  },
  "802d8020-9792-47ed-9b5c-904d89c28b0b": {
    "FBACJKDNMJE": [],
    "KLHFLAODHIE": [],
    "DPNKFDDEGNE": "7d8f7673-5d3b-44ea-bfd3-60443acdd436",
    "NEJBKIJIBHJ": [
      {
        "NKPOOPONEHG": "VO_AQ\\VO_marionette\\vo_NKAQ003_20_marionette_09.wem",
        "FBCCEBGJEDB": "",
        "DAGKBDACGKN": "",
        "OFIPNHHFMIN": 1,
        "ILELCCFFKMG": 0
      }
    ],
    "LNBFOPNLLDB": "802d8020-9792-47ed-9b5c-904d89c28b0b",
    "JOMDCMBGNMB": "Dialog",
    "LDKLLMBOPIL": 0,
    "IHJNILOFHDI": 0,
    "DINIOGNDACL": 1,
    "BKGHEBIGJNC": 60022216,
    "CLILOKOGFCH": 0,
    "OAOMGAPFFMC": 2,
    "FGDBNGAMIBE": 0,
    "NLNHEEOBGLH": 0,
    "ONCKINKBDMD": 0,
    "IEDLBAGHKGK": 0,
    "FBNNIOINNNO": false,
    "HCCLMPGEBLE": false,
    "DJHJHPLAJNG": false,
    "GIAFBIIBGOE": false
  },
  "aaf5f3a7-3444-4e5f-a674-3b7eae7c5a3e": {
    "FBACJKDNMJE": [],
    "KLHFLAODHIE": [],
    "DPNKFDDEGNE": "7d8f7673-5d3b-44ea-bfd3-60443acdd436",
    "NEJBKIJIBHJ": [
      {
        "NKPOOPONEHG": "VO_AQ\\VO_jahoda\\vo_NKAQ003_20_jahoda_01.wem",
        "FBCCEBGJEDB": "",
        "DAGKBDACGKN": "",
        "OFIPNHHFMIN": 1,
        "ILELCCFFKMG": 0
      }
    ],
    "LNBFOPNLLDB": "aaf5f3a7-3444-4e5f-a674-3b7eae7c5a3e",
    "JOMDCMBGNMB": "Dialog",
    "LDKLLMBOPIL": 0,
    "IHJNILOFHDI": 0,
    "DINIOGNDACL": 1,
    "BKGHEBIGJNC": 60022206,
    "CLILOKOGFCH": 0,
    "OAOMGAPFFMC": 2,
    "FGDBNGAMIBE": 0,
    "NLNHEEOBGLH": 0,
    "ONCKINKBDMD": 0,
    "IEDLBAGHKGK": 0,
    "FBNNIOINNNO": false,
    "HCCLMPGEBLE": false,
    "DJHJHPLAJNG": false,
    "GIAFBIIBGOE": false
  },
  "b135cf8e-9167-4f23-951d-0bc85492551a": {
    "FBACJKDNMJE": [],
    "KLHFLAODHIE": [],
    "DPNKFDDEGNE": "7d8f7673-5d3b-44ea-bfd3-60443acdd436",
    "NEJBKIJIBHJ": [
      {
        "NKPOOPONEHG": "VO_AQ\\VO_marionette\\vo_NKAQ003_20_marionette_01.wem",
        "FBCCEBGJEDB": "",
        "DAGKBDACGKN": "",
        "OFIPNHHFMIN": 1,
        "ILELCCFFKMG": 0
      }
    ],
    "LNBFOPNLLDB": "b135cf8e-9167-4f23-951d-0bc85492551a",
    "JOMDCMBGNMB": "Dialog",
    "LDKLLMBOPIL": 0,
    "IHJNILOFHDI": 1,
    "DINIOGNDACL": 1,
    "BKGHEBIGJNC": 60022201,
    "CLILOKOGFCH": 0,
    "OAOMGAPFFMC": 2,
    "FGDBNGAMIBE": 0,
    "NLNHEEOBGLH": 0,
    "ONCKINKBDMD": 0,
    "IEDLBAGHKGK": 0,
    "FBNNIOINNNO": false,
    "HCCLMPGEBLE": false,
    "DJHJHPLAJNG": false,
    "GIAFBIIBGOE": false
  },
  "b2ce4bfc-9da6-40d1-b315-14e669bc59db": {
    "FBACJKDNMJE": [],
    "KLHFLAODHIE": [],
    "DPNKFDDEGNE": "7d8f7673-5d3b-44ea-bfd3-60443acdd436",
    "NEJBKIJIBHJ": [
      {
        "NKPOOPONEHG": "VO_AQ\\VO_jahoda\\vo_NKAQ003_20_jahoda_03.wem",
        "FBCCEBGJEDB": "",
        "DAGKBDACGKN": "",
        "OFIPNHHFMIN": 1,
        "ILELCCFFKMG": 0
      }
    ],
    "LNBFOPNLLDB": "b2ce4bfc-9da6-40d1-b315-14e669bc59db",
    "JOMDCMBGNMB": "Dialog",
    "LDKLLMBOPIL": 0,
    "IHJNILOFHDI": 1,
    "DINIOGNDACL": 1,
    "BKGHEBIGJNC": 60022209,
    "CLILOKOGFCH": 0,
    "OAOMGAPFFMC": 2,
    "FGDBNGAMIBE": 0,
    "NLNHEEOBGLH": 0,
    "ONCKINKBDMD": 0,
    "IEDLBAGHKGK": 0,
    "FBNNIOINNNO": false,
    "HCCLMPGEBLE": false,
    "DJHJHPLAJNG": false,
    "GIAFBIIBGOE": false
  },
  "c1b7210c-8d00-4cbf-9346-4cacb8d0add1": {
    "FBACJKDNMJE": [],
    "KLHFLAODHIE": [],
    "DPNKFDDEGNE": "7d8f7673-5d3b-44ea-bfd3-60443acdd436",
    "NEJBKIJIBHJ": [
      {
        "NKPOOPONEHG": "VO_AQ\\VO_lauma\\vo_NKAQ003_20_lauma_03.wem",
        "FBCCEBGJEDB": "",
        "DAGKBDACGKN": "",
        "OFIPNHHFMIN": 1,
        "ILELCCFFKMG": 0
      }
    ],
    "LNBFOPNLLDB": "c1b7210c-8d00-4cbf-9346-4cacb8d0add1",
    "JOMDCMBGNMB": "Dialog",
    "LDKLLMBOPIL": 0,
    "IHJNILOFHDI": 0,
    "DINIOGNDACL": 1,
    "BKGHEBIGJNC": 60022223,
    "CLILOKOGFCH": 0,
    "OAOMGAPFFMC": 2,
    "FGDBNGAMIBE": 0,
    "NLNHEEOBGLH": 0,
    "ONCKINKBDMD": 0,
    "IEDLBAGHKGK": 0,
    "FBNNIOINNNO": false,
    "HCCLMPGEBLE": false,
    "DJHJHPLAJNG": false,
    "GIAFBIIBGOE": false
  },
  "d6875c8a-9c50-4d27-8708-e320f11f38f6": {
    "FBACJKDNMJE": [],
    "KLHFLAODHIE": [],
    "DPNKFDDEGNE": "7d8f7673-5d3b-44ea-bfd3-60443acdd436",
    "NEJBKIJIBHJ": [
      {
        "NKPOOPONEHG": "VO_AQ\\VO_paimon\\vo_NKAQ003_20_paimon_01.wem",
        "FBCCEBGJEDB": "",
        "DAGKBDACGKN": "",
        "OFIPNHHFMIN": 1,
        "ILELCCFFKMG": 0
      }
    ],
    "LNBFOPNLLDB": "d6875c8a-9c50-4d27-8708-e320f11f38f6",
    "JOMDCMBGNMB": "Dialog",
    "LDKLLMBOPIL": 0,
    "IHJNILOFHDI": 0,
    "DINIOGNDACL": 1,
    "BKGHEBIGJNC": 60022211,
    "CLILOKOGFCH": 0,
    "OAOMGAPFFMC": 2,
    "FGDBNGAMIBE": 0,
    "NLNHEEOBGLH": 0,
    "ONCKINKBDMD": 0,
    "IEDLBAGHKGK": 0,
    "FBNNIOINNNO": false,
    "HCCLMPGEBLE": false,
    "DJHJHPLAJNG": false,
    "GIAFBIIBGOE": false
  },
  "d74ac666-aae5-49e4-bca8-dcc745e88163": {
    "FBACJKDNMJE": [],
    "KLHFLAODHIE": [],
    "DPNKFDDEGNE": "7d8f7673-5d3b-44ea-bfd3-60443acdd436",
    "NEJBKIJIBHJ": [
      {
        "NKPOOPONEHG": "VO_AQ\\VO_NPC\\vo_NKAQ003_20_aarto_01.wem",
        "FBCCEBGJEDB": "",
        "DAGKBDACGKN": "",
        "OFIPNHHFMIN": 1,
        "ILELCCFFKMG": 0
      }
    ],
    "LNBFOPNLLDB": "d74ac666-aae5-49e4-bca8-dcc745e88163",
    "JOMDCMBGNMB": "Dialog",
    "LDKLLMBOPIL": 0,
    "IHJNILOFHDI": 0,
    "DINIOGNDACL": 1,
    "BKGHEBIGJNC": 60022204,
    "CLILOKOGFCH": 0,
    "OAOMGAPFFMC": 2,
    "FGDBNGAMIBE": 0,
    "NLNHEEOBGLH": 0,
    "ONCKINKBDMD": 0,
    "IEDLBAGHKGK": 0,
    "FBNNIOINNNO": false,
    "HCCLMPGEBLE": false,
    "DJHJHPLAJNG": false,
    "GIAFBIIBGOE": false
  },
  "d7b272f4-ebfd-461d-b488-2ae289691447": {
    "FBACJKDNMJE": [],
    "KLHFLAODHIE": [],
    "DPNKFDDEGNE": "7d8f7673-5d3b-44ea-bfd3-60443acdd436",
    "NEJBKIJIBHJ": [
      {
        "NKPOOPONEHG": "VO_AQ\\VO_marionette\\vo_NKAQ003_20_marionette_13.wem",
        "FBCCEBGJEDB": "",
        "DAGKBDACGKN": "",
        "OFIPNHHFMIN": 1,
        "ILELCCFFKMG": 0
      }
    ],
    "LNBFOPNLLDB": "d7b272f4-ebfd-461d-b488-2ae289691447",
    "JOMDCMBGNMB": "Dialog",
    "LDKLLMBOPIL": 0,
    "IHJNILOFHDI": 0,
    "DINIOGNDACL": 1,
    "BKGHEBIGJNC": 60022221,
    "CLILOKOGFCH": 0,
    "OAOMGAPFFMC": 2,
    "FGDBNGAMIBE": 0,
    "NLNHEEOBGLH": 0,
    "ONCKINKBDMD": 0,
    "IEDLBAGHKGK": 0,
    "FBNNIOINNNO": false,
    "HCCLMPGEBLE": false,
    "DJHJHPLAJNG": false,
    "GIAFBIIBGOE": false
  },
  "dfa5d9b8-eb13-4fad-bbef-701486f9b0f5": {
    "FBACJKDNMJE": [],
    "KLHFLAODHIE": [],
    "DPNKFDDEGNE": "7d8f7673-5d3b-44ea-bfd3-60443acdd436",
    "NEJBKIJIBHJ": [
      {
        "NKPOOPONEHG": "VO_AQ\\VO_lauma\\vo_NKAQ003_20_lauma_02.wem",
        "FBCCEBGJEDB": "",
        "DAGKBDACGKN": "",
        "OFIPNHHFMIN": 1,
        "ILELCCFFKMG": 0
      }
    ],
    "LNBFOPNLLDB": "dfa5d9b8-eb13-4fad-bbef-701486f9b0f5",
    "JOMDCMBGNMB": "Dialog",
    "LDKLLMBOPIL": 0,
    "IHJNILOFHDI": 0,
    "DINIOGNDACL": 1,
    "BKGHEBIGJNC": 60022214,
    "CLILOKOGFCH": 0,
    "OAOMGAPFFMC": 2,
    "FGDBNGAMIBE": 0,
    "NLNHEEOBGLH": 0,
    "ONCKINKBDMD": 0,
    "IEDLBAGHKGK": 0,
    "FBNNIOINNNO": false,
    "HCCLMPGEBLE": false,
    "DJHJHPLAJNG": false,
    "GIAFBIIBGOE": false
  },
  "e7e27fe9-e854-4cba-a294-f7a5362a3c2d": {
    "FBACJKDNMJE": [],
    "KLHFLAODHIE": [],
    "DPNKFDDEGNE": "7d8f7673-5d3b-44ea-bfd3-60443acdd436",
    "NEJBKIJIBHJ": [
      {
        "NKPOOPONEHG": "VO_AQ\\VO_marionette\\vo_NKAQ003_20_marionette_12.wem",
        "FBCCEBGJEDB": "",
        "DAGKBDACGKN": "",
        "OFIPNHHFMIN": 1,
        "ILELCCFFKMG": 0
      }
    ],
    "LNBFOPNLLDB": "e7e27fe9-e854-4cba-a294-f7a5362a3c2d",
    "JOMDCMBGNMB": "Dialog",
    "LDKLLMBOPIL": 0,
    "IHJNILOFHDI": 0,
    "DINIOGNDACL": 1,
    "BKGHEBIGJNC": 60022220,
    "CLILOKOGFCH": 0,
    "OAOMGAPFFMC": 2,
    "FGDBNGAMIBE": 0,
    "NLNHEEOBGLH": 0,
    "ONCKINKBDMD": 0,
    "IEDLBAGHKGK": 0,
    "FBNNIOINNNO": false,
    "HCCLMPGEBLE": false,
    "DJHJHPLAJNG": false,
    "GIAFBIIBGOE": false
  },
  "f847757d-ec71-4858-869f-52899eac20e4": {
    "FBACJKDNMJE": [],
    "KLHFLAODHIE": [],
    "DPNKFDDEGNE": "7d8f7673-5d3b-44ea-bfd3-60443acdd436",
    "NEJBKIJIBHJ": [
      {
        "NKPOOPONEHG": "VO_AQ\\VO_marionette\\vo_NKAQ003_20_marionette_10.wem",
        "FBCCEBGJEDB": "",
        "DAGKBDACGKN": "",
        "OFIPNHHFMIN": 1,
        "ILELCCFFKMG": 0
      }
    ],
    "LNBFOPNLLDB": "f847757d-ec71-4858-869f-52899eac20e4",
    "JOMDCMBGNMB": "Dialog",
    "LDKLLMBOPIL": 0,
    "IHJNILOFHDI": 0,
    "DINIOGNDACL": 1,
    "BKGHEBIGJNC": 60022217,
    "CLILOKOGFCH": 0,
    "OAOMGAPFFMC": 2,
    "FGDBNGAMIBE": 0,
    "NLNHEEOBGLH": 0,
    "ONCKINKBDMD": 0,
    "IEDLBAGHKGK": 0,
    "FBNNIOINNNO": false,
    "HCCLMPGEBLE": false,
    "DJHJHPLAJNG": false,
    "GIAFBIIBGOE": false
  },
  "fcde9d03-a198-4a6f-b14e-a72a07a50365": {
    "FBACJKDNMJE": [],
    "KLHFLAODHIE": [],
    "DPNKFDDEGNE": "7d8f7673-5d3b-44ea-bfd3-60443acdd436",
    "NEJBKIJIBHJ": [
      {
        "NKPOOPONEHG": "VO_AQ\\VO_marionette\\vo_NKAQ003_20_marionette_05.wem",
        "FBCCEBGJEDB": "",
        "DAGKBDACGKN": "",
        "OFIPNHHFMIN": 1,
        "ILELCCFFKMG": 0
      }
    ],
    "LNBFOPNLLDB": "fcde9d03-a198-4a6f-b14e-a72a07a50365",
    "JOMDCMBGNMB": "Dialog",
    "LDKLLMBOPIL": 0,
    "IHJNILOFHDI": 0,
    "DINIOGNDACL": 1,
    "BKGHEBIGJNC": 60022208,
    "CLILOKOGFCH": 0,
    "OAOMGAPFFMC": 2,
    "FGDBNGAMIBE": 0,
    "NLNHEEOBGLH": 0,
    "ONCKINKBDMD": 0,
    "IEDLBAGHKGK": 0,
    "FBNNIOINNNO": false,
    "HCCLMPGEBLE": false,
    "DJHJHPLAJNG": false,
    "GIAFBIIBGOE": false
  }
}