{
  "GDDPNNHLGBL": [
    {
      "DMJFNDAOLOF": "",
      "JNJNJKHGOAP": "",
      "LONJFNHGILF": "",
      "LJBALDDMEAF": [],
      "NFNCOJNDLAE": "",
      "HIDAHGHGFNL": "",
      "OMAHHDBCAPB": [
        30320302
      ],
      "IKHKNNDCCPN": "",
      "EENIFNIGHCH": {
        "_id": "12992",
        "_roleId": 0,
        "_type": "TALK_ROLE_NPC"
      },
      "FOKJOAPPOFJ": "",
      "GOCCHCNMEJF": "",
      "GBLIAGAIAAK": 0,
      "DMIFDJDEFAL": 3646157378,
      "ANKFNLMKOII": 30320301,
      "BNIBAOMDMDN": 0,
      "EGKJOKIHBPF": "TALK_SHOW_DEFAULT",
      "OBOMFPCPKEC": 0,
      "MGHAHBJDENK": 0,
      "CBHHMMCNOKC": "DIALOG_UI_NONE",
      "GOOEAHEPFLF": 0
    },
    {
      "DMJFNDAOLOF": "",
      "JNJNJKHGOAP": "",
      "LONJFNHGILF": "",
      "LJBALDDMEAF": [],
      "NFNCOJNDLAE": "",
      "HIDAHGHGFNL": "",
      "OMAHHDBCAPB": [
        30320303
      ],
      "IKHKNNDCCPN": "",
      "EENIFNIGHCH": {
        "_id": "12991",
        "_roleId": 0,
        "_type": "TALK_ROLE_NPC"
      },
      "FOKJOAPPOFJ": "",
      "GOCCHCNMEJF": "",
      "GBLIAGAIAAK": 0,
      "DMIFDJDEFAL": 1034374762,
      "ANKFNLMKOII": 30320302,
      "BNIBAOMDMDN": 0,
      "EGKJOKIHBPF": "TALK_SHOW_DEFAULT",
      "OBOMFPCPKEC": 0,
      "MGHAHBJDENK": 0,
      "CBHHMMCNOKC": "DIALOG_UI_NONE",
      "GOOEAHEPFLF": 0
    },
    {
      "DMJFNDAOLOF": "",
      "JNJNJKHGOAP": "",
      "LONJFNHGILF": "",
      "LJBALDDMEAF": [],
      "NFNCOJNDLAE": "",
      "HIDAHGHGFNL": "",
      "OMAHHDBCAPB": [
        30320304
      ],
      "IKHKNNDCCPN": "",
      "EENIFNIGHCH": {
        "_id": "12992",
        "_roleId": 0,
        "_type": "TALK_ROLE_NPC"
      },
      "FOKJOAPPOFJ": "",
      "GOCCHCNMEJF": "",
      "GBLIAGAIAAK": 0,
      "DMIFDJDEFAL": 1398773738,
      "ANKFNLMKOII": 30320303,
      "BNIBAOMDMDN": 0,
      "EGKJOKIHBPF": "TALK_SHOW_DEFAULT",
      "OBOMFPCPKEC": 0,
      "MGHAHBJDENK": 0,
      "CBHHMMCNOKC": "DIALOG_UI_NONE",
      "GOOEAHEPFLF": 0
    },
    {
      "DMJFNDAOLOF": "",
      "JNJNJKHGOAP": "",
      "LONJFNHGILF": "",
      "LJBALDDMEAF": [],
      "NFNCOJNDLAE": "",
      "HIDAHGHGFNL": "",
      "OMAHHDBCAPB": [
        30320305
      ],
      "IKHKNNDCCPN": "",
      "EENIFNIGHCH": {
        "_id": "12992",
        "_roleId": 0,
        "_type": "TALK_ROLE_NPC"
      },
      "FOKJOAPPOFJ": "",
      "GOCCHCNMEJF": "",
      "GBLIAGAIAAK": 0,
      "DMIFDJDEFAL": 4154252978,
      "ANKFNLMKOII": 30320304,
      "BNIBAOMDMDN": 0,
      "EGKJOKIHBPF": "TALK_SHOW_DEFAULT",
      "OBOMFPCPKEC": 0,
      "MGHAHBJDENK": 0,
      "CBHHMMCNOKC": "DIALOG_UI_NONE",
      "GOOEAHEPFLF": 0
    },
    {
      "DMJFNDAOLOF": "",
      "JNJNJKHGOAP": "",
      "LONJFNHGILF": "",
      "LJBALDDMEAF": [],
      "NFNCOJNDLAE": "",
      "HIDAHGHGFNL": "",
      "OMAHHDBCAPB": [
        30320306
      ],
      "IKHKNNDCCPN": "",
      "EENIFNIGHCH": {
        "_id": "12992",
        "_roleId": 0,
        "_type": "TALK_ROLE_NPC"
      },
      "FOKJOAPPOFJ": "",
      "GOCCHCNMEJF": "",
      "GBLIAGAIAAK": 0,
      "DMIFDJDEFAL": 1175534234,
      "ANKFNLMKOII": 30320305,
      "BNIBAOMDMDN": 0,
      "EGKJOKIHBPF": "TALK_SHOW_DEFAULT",
      "OBOMFPCPKEC": 0,
      "MGHAHBJDENK": 0,
      "CBHHMMCNOKC": "DIALOG_UI_NONE",
      "GOOEAHEPFLF": 0
    },
    {
      "DMJFNDAOLOF": "",
      "JNJNJKHGOAP": "",
      "LONJFNHGILF": "",
      "LJBALDDMEAF": [],
      "NFNCOJNDLAE": "",
      "HIDAHGHGFNL": "",
      "OMAHHDBCAPB": [
        30320307
      ],
      "IKHKNNDCCPN": "",
      "EENIFNIGHCH": {
        "_id": "12992",
        "_roleId": 0,
        "_type": "TALK_ROLE_NPC"
      },
      "FOKJOAPPOFJ": "",
      "GOCCHCNMEJF": "",
      "GBLIAGAIAAK": 0,
      "DMIFDJDEFAL": 2055258794,
      "ANKFNLMKOII": 30320306,
      "BNIBAOMDMDN": 0,
      "EGKJOKIHBPF": "TALK_SHOW_DEFAULT",
      "OBOMFPCPKEC": 0,
      "MGHAHBJDENK": 0,
      "CBHHMMCNOKC": "DIALOG_UI_NONE",
      "GOOEAHEPFLF": 0
    },
    {
      "DMJFNDAOLOF": "",
      "JNJNJKHGOAP": "",
      "LONJFNHGILF": "",
      "LJBALDDMEAF": [],
      "NFNCOJNDLAE": "",
      "HIDAHGHGFNL": "",
      "OMAHHDBCAPB": [
        30320308
      ],
      "IKHKNNDCCPN": "",
      "EENIFNIGHCH": {
        "_id": "12992",
        "_roleId": 0,
        "_type": "TALK_ROLE_NPC"
      },
      "FOKJOAPPOFJ": "",
      "GOCCHCNMEJF": "",
      "GBLIAGAIAAK": 0,
      "DMIFDJDEFAL": 415213402,
      "ANKFNLMKOII": 30320307,
      "BNIBAOMDMDN": 0,
      "EGKJOKIHBPF": "TALK_SHOW_DEFAULT",
      "OBOMFPCPKEC": 0,
      "MGHAHBJDENK": 0,
      "CBHHMMCNOKC": "DIALOG_UI_NONE",
      "GOOEAHEPFLF": 0
    },
    {
      "DMJFNDAOLOF": "",
      "JNJNJKHGOAP": "",
      "LONJFNHGILF": "",
      "LJBALDDMEAF": [],
      "NFNCOJNDLAE": "",
      "HIDAHGHGFNL": "",
      "OMAHHDBCAPB": [],
      "IKHKNNDCCPN": "",
      "EENIFNIGHCH": {
        "_id": "1065",
        "_roleId": 0,
        "_type": "TALK_ROLE_NPC"
      },
      "FOKJOAPPOFJ": "",
      "GOCCHCNMEJF": "",
      "GBLIAGAIAAK": 0,
      "DMIFDJDEFAL": 262552346,
      "ANKFNLMKOII": 30320308,
      "BNIBAOMDMDN": 0,
      "EGKJOKIHBPF": "TALK_SHOW_DEFAULT",
      "OBOMFPCPKEC": 0,
      "MGHAHBJDENK": 0,
      "CBHHMMCNOKC": "DIALOG_UI_NONE",
      "GOOEAHEPFLF": 0
    }
  ],
  "LDLMECNIJFC": 303203,
  "BPEHONLLNNK": "QUEST"
}