{
    "DLPKMDPABFM": "QUEST",
    "LBPGKDMGFBN": 602766,
    "LOJEOMAPIIM": [
      {
        "BAGJEMDHGNC": 0,
        "BJOBBKENFIN": "",
        "BLKKAMEMBBJ": 60276601,
        "CMKPOJOEHHA": 290657178,
        "DCFNDLJAAII": "",
        "FLCJOHFLGND": [],
        "HCNAAJINHFH": "DIALOG_UI_NONE",
        "HJIPOJOECIF": {
          "_id": "16100",
          "_roleId": 0,
          "_type": "TALK_ROLE_NPC"
        },
        "ICPKBBAAJDK": [
          60276602
        ],
        "INMDHFPHKGC": 0,
        "JALMPOOOPFJ": "",
        "KEBCGBCFIEI": "",
        "KECAAAADLJK": "TALK_SHOW_DEFAULT",
        "LBMEGCDGDLN": 0,
        "MDAEOALOCMN": "",
        "OBABNOAFFGP": "",
        "OJOJJAIELKK": "",
        "PELBMPLIEKC": 0,
        "PHCPJPJJLGI": ""
      },
      {
        "BAGJEMDHGNC": 0,
        "BJOBBKENFIN": "",
        "BLKKAMEMBBJ": 60276602,
        "CMKPOJOEHHA": 2896471282,
        "DCFNDLJAAII": "",
        "FLCJOHFLGND": [],
        "HCNAAJINHFH": "DIALOG_UI_NONE",
        "HJIPOJOECIF": {
          "_id": "16100",
          "_roleId": 0,
          "_type": "TALK_ROLE_NPC"
        },
        "ICPKBBAAJDK": [
          60276603,
          60276606,
          60276608
        ],
        "INMDHFPHKGC": 0,
        "JALMPOOOPFJ": "",
        "KEBCGBCFIEI": "",
        "KECAAAADLJK": "TALK_SHOW_DEFAULT",
        "LBMEGCDGDLN": 0,
        "MDAEOALOCMN": "",
        "OBABNOAFFGP": "",
        "OJOJJAIELKK": "",
        "PELBMPLIEKC": 0,
        "PHCPJPJJLGI": ""
      },
      {
        "BAGJEMDHGNC": 0,
        "BJOBBKENFIN": "",
        "BLKKAMEMBBJ": 60276603,
        "CMKPOJOEHHA": 1436851522,
        "DCFNDLJAAII": "",
        "FLCJOHFLGND": [],
        "HCNAAJINHFH": "DIALOG_UI_NONE",
        "HJIPOJOECIF": {
          "_id": "1318",
          "_roleId": 0,
          "_type": "TALK_ROLE_NPC"
        },
        "ICPKBBAAJDK": [
          60276604
        ],
        "INMDHFPHKGC": 0,
        "JALMPOOOPFJ": "",
        "KEBCGBCFIEI": "",
        "KECAAAADLJK": "TALK_SHOW_DEFAULT",
        "LBMEGCDGDLN": 0,
        "MDAEOALOCMN": "",
        "OBABNOAFFGP": "",
        "OJOJJAIELKK": "",
        "PELBMPLIEKC": 0,
        "PHCPJPJJLGI": ""
      },
      {
        "BAGJEMDHGNC": 0,
        "BJOBBKENFIN": "",
        "BLKKAMEMBBJ": 60276604,
        "CMKPOJOEHHA": 1868144882,
        "DCFNDLJAAII": "",
        "FLCJOHFLGND": [],
        "HCNAAJINHFH": "DIALOG_UI_NONE",
        "HJIPOJOECIF": {
          "_id": "16100",
          "_roleId": 0,
          "_type": "TALK_ROLE_NPC"
        },
        "ICPKBBAAJDK": [
          60276605
        ],
        "INMDHFPHKGC": 0,
        "JALMPOOOPFJ": "",
        "KEBCGBCFIEI": "",
        "KECAAAADLJK": "TALK_SHOW_DEFAULT",
        "LBMEGCDGDLN": 0,
        "MDAEOALOCMN": "",
        "OBABNOAFFGP": "",
        "OJOJJAIELKK": "",
        "PELBMPLIEKC": 0,
        "PHCPJPJJLGI": ""
      },
      {
        "BAGJEMDHGNC": 0,
        "BJOBBKENFIN": "",
        "BLKKAMEMBBJ": 60276605,
        "CMKPOJOEHHA": 1092540530,
        "DCFNDLJAAII": "",
        "FLCJOHFLGND": [],
        "HCNAAJINHFH": "DIALOG_UI_NONE",
        "HJIPOJOECIF": {
          "_id": "16100",
          "_roleId": 0,
          "_type": "TALK_ROLE_NPC"
        },
        "ICPKBBAAJDK": [],
        "INMDHFPHKGC": 0,
        "JALMPOOOPFJ": "",
        "KEBCGBCFIEI": "",
        "KECAAAADLJK": "TALK_SHOW_DEFAULT",
        "LBMEGCDGDLN": 0,
        "MDAEOALOCMN": "",
        "OBABNOAFFGP": "",
        "OJOJJAIELKK": "",
        "PELBMPLIEKC": 0,
        "PHCPJPJJLGI": ""
      },
      {
        "BAGJEMDHGNC": 0,
        "BJOBBKENFIN": "",
        "BLKKAMEMBBJ": 60276606,
        "CMKPOJOEHHA": 1164639386,
        "DCFNDLJAAII": "",
        "FLCJOHFLGND": [],
        "HCNAAJINHFH": "DIALOG_UI_NONE",
        "HJIPOJOECIF": {
          "_id": "1318",
          "_roleId": 0,
          "_type": "TALK_ROLE_NPC"
        },
        "ICPKBBAAJDK": [
          60276607
        ],
        "INMDHFPHKGC": 0,
        "JALMPOOOPFJ": "",
        "KEBCGBCFIEI": "",
        "KECAAAADLJK": "TALK_SHOW_DEFAULT",
        "LBMEGCDGDLN": 0,
        "MDAEOALOCMN": "",
        "OBABNOAFFGP": "",
        "OJOJJAIELKK": "",
        "PELBMPLIEKC": 0,
        "PHCPJPJJLGI": ""
      },
      {
        "BAGJEMDHGNC": 0,
        "BJOBBKENFIN": "",
        "BLKKAMEMBBJ": 60276607,
        "CMKPOJOEHHA": 1009133610,
        "DCFNDLJAAII": "",
        "FLCJOHFLGND": [],
        "HCNAAJINHFH": "DIALOG_UI_NONE",
        "HJIPOJOECIF": {
          "_id": "16100",
          "_roleId": 0,
          "_type": "TALK_ROLE_NPC"
        },
        "ICPKBBAAJDK": [],
        "INMDHFPHKGC": 0,
        "JALMPOOOPFJ": "",
        "KEBCGBCFIEI": "",
        "KECAAAADLJK": "TALK_SHOW_DEFAULT",
        "LBMEGCDGDLN": 0,
        "MDAEOALOCMN": "",
        "OBABNOAFFGP": "",
        "OJOJJAIELKK": "",
        "PELBMPLIEKC": 0,
        "PHCPJPJJLGI": ""
      },
      {
        "BAGJEMDHGNC": 0,
        "BJOBBKENFIN": "",
        "BLKKAMEMBBJ": 60276608,
        "CMKPOJOEHHA": 2859807522,
        "DCFNDLJAAII": "",
        "FLCJOHFLGND": [],
        "HCNAAJINHFH": "DIALOG_UI_NONE",
        "HJIPOJOECIF": {
          "_id": "",
          "_roleId": 0,
          "_type": "TALK_ROLE_PLAYER"
        },
        "ICPKBBAAJDK": [
          60276609
        ],
        "INMDHFPHKGC": 0,
        "JALMPOOOPFJ": "",
        "KEBCGBCFIEI": "",
        "KECAAAADLJK": "TALK_SHOW_DEFAULT",
        "LBMEGCDGDLN": 0,
        "MDAEOALOCMN": "",
        "OBABNOAFFGP": "",
        "OJOJJAIELKK": "",
        "PELBMPLIEKC": 0,
        "PHCPJPJJLGI": ""
      },
      {
        "BAGJEMDHGNC": 0,
        "BJOBBKENFIN": "",
        "BLKKAMEMBBJ": 60276609,
        "CMKPOJOEHHA": 4085986274,
        "DCFNDLJAAII": "",
        "FLCJOHFLGND": [],
        "HCNAAJINHFH": "DIALOG_UI_NONE",
        "HJIPOJOECIF": {
          "_id": "16100",
          "_roleId": 0,
          "_type": "TALK_ROLE_NPC"
        },
        "ICPKBBAAJDK": [
          60276610
        ],
        "INMDHFPHKGC": 0,
        "JALMPOOOPFJ": "",
        "KEBCGBCFIEI": "",
        "KECAAAADLJK": "TALK_SHOW_DEFAULT",
        "LBMEGCDGDLN": 0,
        "MDAEOALOCMN": "",
        "OBABNOAFFGP": "",
        "OJOJJAIELKK": "",
        "PELBMPLIEKC": 0,
        "PHCPJPJJLGI": ""
      },
      {
        "BAGJEMDHGNC": 0,
        "BJOBBKENFIN": "",
        "BLKKAMEMBBJ": 60276610,
        "CMKPOJOEHHA": 3961432002,
        "DCFNDLJAAII": "",
        "FLCJOHFLGND": [],
        "HCNAAJINHFH": "DIALOG_UI_NONE",
        "HJIPOJOECIF": {
          "_id": "16100",
          "_roleId": 0,
          "_type": "TALK_ROLE_NPC"
        },
        "ICPKBBAAJDK": [
          60276611
        ],
        "INMDHFPHKGC": 0,
        "JALMPOOOPFJ": "",
        "KEBCGBCFIEI": "",
        "KECAAAADLJK": "TALK_SHOW_DEFAULT",
        "LBMEGCDGDLN": 0,
        "MDAEOALOCMN": "",
        "OBABNOAFFGP": "",
        "OJOJJAIELKK": "",
        "PELBMPLIEKC": 0,
        "PHCPJPJJLGI": ""
      },
      {
        "BAGJEMDHGNC": 0,
        "BJOBBKENFIN": "",
        "BLKKAMEMBBJ": 60276611,
        "CMKPOJOEHHA": 2194028586,
        "DCFNDLJAAII": "",
        "FLCJOHFLGND": [],
        "HCNAAJINHFH": "DIALOG_UI_NONE",
        "HJIPOJOECIF": {
          "_id": "16100",
          "_roleId": 0,
          "_type": "TALK_ROLE_NPC"
        },
        "ICPKBBAAJDK": [
          60276612
        ],
        "INMDHFPHKGC": 0,
        "JALMPOOOPFJ": "",
        "KEBCGBCFIEI": "",
        "KECAAAADLJK": "TALK_SHOW_DEFAULT",
        "LBMEGCDGDLN": 0,
        "MDAEOALOCMN": "",
        "OBABNOAFFGP": "",
        "OJOJJAIELKK": "",
        "PELBMPLIEKC": 0,
        "PHCPJPJJLGI": ""
      },
      {
        "BAGJEMDHGNC": 0,
        "BJOBBKENFIN": "",
        "BLKKAMEMBBJ": 60276612,
        "CMKPOJOEHHA": 3058200298,
        "DCFNDLJAAII": "",
        "FLCJOHFLGND": [],
        "HCNAAJINHFH": "DIALOG_UI_NONE",
        "HJIPOJOECIF": {
          "_id": "16100",
          "_roleId": 0,
          "_type": "TALK_ROLE_NPC"
        },
        "ICPKBBAAJDK": [],
        "INMDHFPHKGC": 0,
        "JALMPOOOPFJ": "",
        "KEBCGBCFIEI": "",
        "KECAAAADLJK": "TALK_SHOW_DEFAULT",
        "LBMEGCDGDLN": 0,
        "MDAEOALOCMN": "",
        "OBABNOAFFGP": "",
        "OJOJJAIELKK": "",
        "PELBMPLIEKC": 0,
        "PHCPJPJJLGI": ""
      }
    ]
  }