{
    "DLPKMDPABFM": "QUEST",
    "LBPGKDMGFBN": 7104211,
    "LOJEOMAPIIM": [
      {
        "BAGJEMDHGNC": 0,
        "BJOBBKENFIN": "",
        "BLKKAMEMBBJ": 710421101,
        "CMKPOJOEHHA": 61933826,
        "DCFNDLJAAII": "",
        "FLCJOHFLGND": [],
        "HCNAAJINHFH": "DIALOG_UI_NONE",
        "HJIPOJOECIF": {
          "_id": "2617",
          "_roleId": 0,
          "_type": "TALK_ROLE_NPC"
        },
        "ICPKBBAAJDK": [
          710421102,
          710421103
        ],
        "INMDHFPHKGC": 0,
        "JALMPOOOPFJ": "",
        "KEBCGBCFIEI": "",
        "KECAAAADLJK": "TALK_SHOW_DEFAULT",
        "LBMEGCDGDLN": 0,
        "MDAEOALOCMN": "",
        "OBABNOAFFGP": "",
        "OJOJJAIELKK": "",
        "PELBMPLIEKC": 0,
        "PHCPJPJJLGI": ""
      },
      {
        "BAGJEMDHGNC": 0,
        "BJOBBKENFIN": "",
        "BLKKAMEMBBJ": 710421102,
        "CMKPOJOEHHA": 1872028106,
        "DCFNDLJAAII": "",
        "FLCJOHFLGND": [],
        "HCNAAJINHFH": "DIALOG_UI_NONE",
        "HJIPOJOECIF": {
          "_id": "",
          "_roleId": 0,
          "_type": "TALK_ROLE_PLAYER"
        },
        "ICPKBBAAJDK": [
          710421104
        ],
        "INMDHFPHKGC": 0,
        "JALMPOOOPFJ": "",
        "KEBCGBCFIEI": "",
        "KECAAAADLJK": "TALK_SHOW_FORCE_SELECT",
        "LBMEGCDGDLN": 0,
        "MDAEOALOCMN": "",
        "OBABNOAFFGP": "",
        "OJOJJAIELKK": "",
        "PELBMPLIEKC": 0,
        "PHCPJPJJLGI": ""
      },
      {
        "BAGJEMDHGNC": 0,
        "BJOBBKENFIN": "",
        "BLKKAMEMBBJ": 710421104,
        "CMKPOJOEHHA": 3319726058,
        "DCFNDLJAAII": "",
        "FLCJOHFLGND": [],
        "HCNAAJINHFH": "DIALOG_UI_NONE",
        "HJIPOJOECIF": {
          "_id": "2617",
          "_roleId": 0,
          "_type": "TALK_ROLE_NPC"
        },
        "ICPKBBAAJDK": [],
        "INMDHFPHKGC": 0,
        "JALMPOOOPFJ": "",
        "KEBCGBCFIEI": "",
        "KECAAAADLJK": "TALK_SHOW_DEFAULT",
        "LBMEGCDGDLN": 0,
        "MDAEOALOCMN": "",
        "OBABNOAFFGP": "",
        "OJOJJAIELKK": "",
        "PELBMPLIEKC": 0,
        "PHCPJPJJLGI": ""
      },
      {
        "BAGJEMDHGNC": 0,
        "BJOBBKENFIN": "",
        "BLKKAMEMBBJ": 710421103,
        "CMKPOJOEHHA": 3217146962,
        "DCFNDLJAAII": "",
        "FLCJOHFLGND": [],
        "HCNAAJINHFH": "DIALOG_UI_NONE",
        "HJIPOJOECIF": {
          "_id": "",
          "_roleId": 0,
          "_type": "TALK_ROLE_PLAYER"
        },
        "ICPKBBAAJDK": [
          710421105
        ],
        "INMDHFPHKGC": 0,
        "JALMPOOOPFJ": "",
        "KEBCGBCFIEI": "",
        "KECAAAADLJK": "TALK_SHOW_FORCE_SELECT",
        "LBMEGCDGDLN": 0,
        "MDAEOALOCMN": "",
        "OBABNOAFFGP": "",
        "OJOJJAIELKK": "",
        "PELBMPLIEKC": 0,
        "PHCPJPJJLGI": ""
      },
      {
        "BAGJEMDHGNC": 0,
        "BJOBBKENFIN": "",
        "BLKKAMEMBBJ": 710421105,
        "CMKPOJOEHHA": 1745286642,
        "DCFNDLJAAII": "",
        "FLCJOHFLGND": [],
        "HCNAAJINHFH": "DIALOG_UI_NONE",
        "HJIPOJOECIF": {
          "_id": "",
          "_roleId": 0,
          "_type": "TALK_ROLE_PLAYER"
        },
        "ICPKBBAAJDK": [
          710421106
        ],
        "INMDHFPHKGC": 0,
        "JALMPOOOPFJ": "",
        "KEBCGBCFIEI": "",
        "KECAAAADLJK": "TALK_SHOW_FORCE_SELECT",
        "LBMEGCDGDLN": 0,
        "MDAEOALOCMN": "",
        "OBABNOAFFGP": "",
        "OJOJJAIELKK": "",
        "PELBMPLIEKC": 0,
        "PHCPJPJJLGI": ""
      },
      {
        "BAGJEMDHGNC": 0,
        "BJOBBKENFIN": "",
        "BLKKAMEMBBJ": 710421106,
        "CMKPOJOEHHA": 792477490,
        "DCFNDLJAAII": "",
        "FLCJOHFLGND": [],
        "HCNAAJINHFH": "DIALOG_UI_NONE",
        "HJIPOJOECIF": {
          "_id": "2617",
          "_roleId": 0,
          "_type": "TALK_ROLE_NPC"
        },
        "ICPKBBAAJDK": [
          710421107
        ],
        "INMDHFPHKGC": 0,
        "JALMPOOOPFJ": "",
        "KEBCGBCFIEI": "",
        "KECAAAADLJK": "TALK_SHOW_DEFAULT",
        "LBMEGCDGDLN": 0,
        "MDAEOALOCMN": "",
        "OBABNOAFFGP": "",
        "OJOJJAIELKK": "",
        "PELBMPLIEKC": 0,
        "PHCPJPJJLGI": ""
      },
      {
        "BAGJEMDHGNC": 0,
        "BJOBBKENFIN": "",
        "BLKKAMEMBBJ": 710421107,
        "CMKPOJOEHHA": 716233834,
        "DCFNDLJAAII": "",
        "FLCJOHFLGND": [],
        "HCNAAJINHFH": "DIALOG_UI_NONE",
        "HJIPOJOECIF": {
          "_id": "2617",
          "_roleId": 0,
          "_type": "TALK_ROLE_NPC"
        },
        "ICPKBBAAJDK": [],
        "INMDHFPHKGC": 0,
        "JALMPOOOPFJ": "",
        "KEBCGBCFIEI": "",
        "KECAAAADLJK": "TALK_SHOW_DEFAULT",
        "LBMEGCDGDLN": 0,
        "MDAEOALOCMN": "",
        "OBABNOAFFGP": "",
        "OJOJJAIELKK": "",
        "PELBMPLIEKC": 0,
        "PHCPJPJJLGI": ""
      }
    ]
  }